mag/__init__.py
mag/dyn_import.py
mag/mag.py
mag/version.py
mag/mag_core/__init__.py
mag/mag_core/launch.py
mag/mag_core/options.py
mag/mag_core/ports.py
mag/mag_core/random.py
mag/mag_core/realm.py
mag/mag_core/std_aliases.py
mag/mag_core/validators.py
mag_dagster/__init__.py
mag_dagster/dagster.py
mag_daskhub/__init__.py
mag_daskhub/daskhub.py
mag_drill/__init__.py
mag_drill/drill.py
mag_minio/__init__.py
mag_minio/mc.py
mag_minio/minio.py
mag_minio/minio_options.py
mag_superset/__init__.py
mag_superset/superset.py
mag_cli-0.1.1.dist-info/LICENSE
mag_cli-0.1.1.dist-info/METADATA
mag_cli-0.1.1.dist-info/WHEEL
mag_cli-0.1.1.dist-info/entry_points.txt
mag_cli-0.1.1.dist-info/top_level.txt
mag_cli-0.1.1.dist-info/RECORD
