Metadata-Version: 2.1
Name: mag-cli
Version: 0.1.1
Summary: Eases the tasks of managing a magasin instance. The glue between components.
Home-page: https://github.com/unicef/magasin
Author: merlos
License: Apache-2.0
License-File: LICENSE
Requires-Dist: Click ==8.1.7
Requires-Dist: click-aliases ==1.0.4
Requires-Dist: requests
Provides-Extra: dev
Requires-Dist: pytest ; extra == 'dev'
Requires-Dist: coverage ; extra == 'dev'
